py_pagseguro/pagseguro.py
py_pagseguro/exceptions.py
py_pagseguro/__init__.py
py_pag/pagseguro.py
py_pag/exceptions.py
py_pag/__init__.py
py_pag-0.1.1.dist-info/metadata.json
py_pag-0.1.1.dist-info/DESCRIPTION.rst
py_pag-0.1.1.dist-info/METADATA
py_pag-0.1.1.dist-info/pbr.json
py_pag-0.1.1.dist-info/RECORD
py_pag-0.1.1.dist-info/top_level.txt
py_pag-0.1.1.dist-info/WHEEL
