Metadata-Version: 2.0
Name: py-pag
Version: 0.1.1
Summary: PagSeguro lib that suports manual subscriptions
Home-page: https://github.com/mbodock/py-pag
Author: Mbodock
Author-email: mbodock@gmail.com
License: MIT
Keywords: pagseguro subscription
Platform: UNKNOWN
Classifier: Development Status :: 3 - Alpha
Classifier: Intended Audience :: Developers
Classifier: License :: OSI Approved :: MIT License
Requires-Dist: arrow
Requires-Dist: beautifulsoup4
Requires-Dist: requests
Requires-Dist: Unidecode
